tsorted/__init__.py
tsorted-0.1.0.data/data/LICENSE.txt
tsorted-0.1.0.data/data/README.md
tsorted-0.1.0.data/data/VERSION
tsorted-0.1.0.dist-info/LICENSE.txt
tsorted-0.1.0.dist-info/METADATA
tsorted-0.1.0.dist-info/WHEEL
tsorted-0.1.0.dist-info/top_level.txt
tsorted-0.1.0.dist-info/RECORD
