Metadata-Version: 2.1
Name: tsorted
Version: 0.1.0
Summary: TSorted lets you sort your data topologically, such as for dependency resolution or task management.
Home-page: https://github.com/bartfeenstra/tsorted
Author: Bart Feenstra & contributors
Author-email: bart@mynameisbart.com
License: MIT
Platform: UNKNOWN
Classifier: License :: OSI Approved :: MIT License
Classifier: Programming Language :: Python :: 3.6
Classifier: Programming Language :: Python :: 3.7
Classifier: Programming Language :: Python :: 3.8
Classifier: Programming Language :: Python :: 3.9
Requires-Python: ~= 3.6
Requires-Dist: orderedset (~=2.0)
Provides-Extra: development
Requires-Dist: autopep8 (~=1.5) ; extra == 'development'
Requires-Dist: codecov (~=2.1) ; extra == 'development'
Requires-Dist: coverage (~=5.5) ; extra == 'development'
Requires-Dist: flake8 (~=3.7.0) ; extra == 'development'
Requires-Dist: pytest (~=6.2.2) ; extra == 'development'
Requires-Dist: setuptools (~=54.2) ; extra == 'development'
Requires-Dist: twine (~=3.4) ; extra == 'development'
Requires-Dist: wheel (~=0.36) ; extra == 'development'
